mpfd/MakeParallel.py
mpfd/__init__.py
mpfd-0.6.0.dist-info/LICENSE
mpfd-0.6.0.dist-info/METADATA
mpfd-0.6.0.dist-info/WHEEL
mpfd-0.6.0.dist-info/top_level.txt
mpfd-0.6.0.dist-info/RECORD
