Metadata-Version: 2.1
Name: mpfd
Version: 0.6.0
Summary: A decorator that makes a function into a parallel processor using multithreading.
Home-page: https://github.com/alloc7260/mpfd
Author: Pranav Hirani
Author-email: pranavpatel7260@gmail.com
License: MIT
Classifier: Programming Language :: Python :: 3
Classifier: License :: OSI Approved :: MIT License
Classifier: Operating System :: OS Independent
Requires-Python: >=3.8
License-File: LICENSE
